rendascii/__init__.py
rendascii/interface.py
rendascii/resource.py
rendascii/utility.py
rendascii/geometry/__init__.py
rendascii/geometry/matrix.py
rendascii/geometry/polygon.py
rendascii/geometry/vector.py
rendascii/pipeline/__init__.py
rendascii/pipeline/shader.py
rendascii/pipeline/stage.py
rendascii-1.0.0a3.dist-info/LICENSE.txt
rendascii-1.0.0a3.dist-info/METADATA
rendascii-1.0.0a3.dist-info/WHEEL
rendascii-1.0.0a3.dist-info/top_level.txt
rendascii-1.0.0a3.dist-info/RECORD
