Metadata-Version: 2.1
Name: rendascii
Version: 1.0.0a3
Summary: Real-time ASCII 3D rendering engine
Home-page: https://github.com/Foxbud/rendascii
Author: Garrett Fairburn
Author-email: garrett@fairburn.dev
License: MIT
Platform: UNKNOWN
Classifier: Programming Language :: Python :: 3
Classifier: License :: OSI Approved :: MIT License
Classifier: Operating System :: OS Independent
Classifier: Environment :: Console
Classifier: Topic :: Multimedia :: Graphics :: 3D Rendering
Classifier: Development Status :: 3 - Alpha
Classifier: Intended Audience :: Developers
Classifier: Natural Language :: English
